LICENSE
MANIFEST.in
README.md
setup.py
tests/__init__.py
tests/http_response_catcher.py
tests/test_helper.py
tests/controllers/__init__.py
tests/controllers/controller_test_base.py
tests/controllers/test_api_controller.py
xmuznlwtyr/__init__.py
xmuznlwtyr/api_helper.py
xmuznlwtyr/configuration.py
xmuznlwtyr/decorators.py
xmuznlwtyr/xmuznlwtyr_client.py
xmuznlwtyr.egg-info/PKG-INFO
xmuznlwtyr.egg-info/SOURCES.txt
xmuznlwtyr.egg-info/dependency_links.txt
xmuznlwtyr.egg-info/requires.txt
xmuznlwtyr.egg-info/top_level.txt
xmuznlwtyr/controllers/__init__.py
xmuznlwtyr/controllers/api_controller.py
xmuznlwtyr/controllers/base_controller.py
xmuznlwtyr/exceptions/__init__.py
xmuznlwtyr/exceptions/api_exception.py
xmuznlwtyr/http/__init__.py
xmuznlwtyr/http/http_call_back.py
xmuznlwtyr/http/http_client.py
xmuznlwtyr/http/http_context.py
xmuznlwtyr/http/http_method_enum.py
xmuznlwtyr/http/http_request.py
xmuznlwtyr/http/http_response.py
xmuznlwtyr/http/requests_client.py
xmuznlwtyr/http/auth/__init__.py
xmuznlwtyr/http/auth/basic_auth.py
xmuznlwtyr/models/__init__.py
xmuznlwtyr/models/suite_code_enum.py